managex_xml_sdk/README.md
managex_xml_sdk/__init__.py
managex_xml_sdk/exceptions.py
managex_xml_sdk/setup.py
managex_xml_sdk/core/__init__.py
managex_xml_sdk/core/certificate_manager.py
managex_xml_sdk/core/validators.py
managex_xml_sdk/core/xml_signer.py
managex_xml_sdk/core/xml_signing.py
managex_xml_sdk/examples/advanced_usage.py
managex_xml_sdk/examples/basic_usage.py
managex_xml_sdk/models/__init__.py
managex_xml_sdk/models/certificate_models.py
managex_xml_sdk/models/signature_models.py
managex_xml_sdk/signers/__init__.py
managex_xml_sdk/signers/hsm_signer.py
managex_xml_sdk/signers/pfx_signer.py
managex_xml_sdk/signers/windows_store_signer.py
managex_xml_sdk-1.0.2.dist-info/licenses/LICENSE
managex_xml_sdk-1.0.2.dist-info/METADATA
managex_xml_sdk-1.0.2.dist-info/WHEEL
managex_xml_sdk-1.0.2.dist-info/entry_points.txt
managex_xml_sdk-1.0.2.dist-info/top_level.txt
managex_xml_sdk-1.0.2.dist-info/RECORD
