Metadata-Version: 2.4
Name: managex-xml-sdk
Version: 1.0.2
Summary: A comprehensive Python SDK for digital certificate management and XML digital signing
Home-page: https://github.com/Aniketc068/managex_xml_sdk
Author: Aniket Chaturvedi
Author-email: Aniket Chaturvedi <chaturvedianiket007@gmail.com>
Maintainer: Aniket Chaturvedi
Maintainer-email: Aniket Chaturvedi <chaturvedianiket007@gmail.com>
License: MIT
Project-URL: Homepage, https://github.com/Aniketc068/managex_xml_sdk
Project-URL: Bug Reports, https://github.com/Aniketc068/managex_xml_sdk/issues
Project-URL: Source, https://github.com/Aniketc068/managex_xml_sdk
Project-URL: Documentation, https://github.com/Aniketc068/managex_xml_sdk/wiki
Project-URL: Discussions, https://github.com/Aniketc068/managex_xml_sdk/discussions
Keywords: xml,digital-signature,certificate,pkcs11,hsm,pfx,windows-store,cryptography,security,signing,managex,enterprise,pki
Platform: any
Classifier: Development Status :: 5 - Production/Stable
Classifier: Intended Audience :: Developers
Classifier: Intended Audience :: Information Technology
Classifier: Intended Audience :: System Administrators
Classifier: Topic :: Security :: Cryptography
Classifier: Topic :: Software Development :: Libraries :: Python Modules
Classifier: Topic :: Text Processing :: Markup :: XML
Classifier: Topic :: Office/Business
Classifier: License :: OSI Approved :: MIT License
Classifier: Programming Language :: Python :: 3
Classifier: Programming Language :: Python :: 3.8
Classifier: Programming Language :: Python :: 3.9
Classifier: Programming Language :: Python :: 3.10
Classifier: Programming Language :: Python :: 3.11
Classifier: Programming Language :: Python :: 3.12
Classifier: Operating System :: OS Independent
Classifier: Operating System :: Microsoft :: Windows
Classifier: Operating System :: POSIX :: Linux
Classifier: Operating System :: MacOS
Classifier: Environment :: Console
Classifier: Environment :: Win32 (MS Windows)
Requires-Python: >=3.8
License-File: LICENSE
Requires-Dist: cryptography>=3.4.8
Requires-Dist: lxml>=4.6.3
Requires-Dist: requests>=2.25.1
Provides-Extra: windows
Requires-Dist: pywin32>=228; extra == "windows"
Provides-Extra: hsm
Requires-Dist: PyKCS11>=1.5.12; extra == "hsm"
Provides-Extra: dev
Requires-Dist: pytest>=6.2.5; extra == "dev"
Requires-Dist: pytest-cov>=2.12.1; extra == "dev"
Requires-Dist: black>=21.9b0; extra == "dev"
Requires-Dist: flake8>=3.9.2; extra == "dev"
Requires-Dist: mypy>=0.910; extra == "dev"
Provides-Extra: docs
Requires-Dist: sphinx>=4.2.0; extra == "docs"
Requires-Dist: sphinx-rtd-theme>=1.0.0; extra == "docs"
Provides-Extra: all
Requires-Dist: pywin32>=228; extra == "all"
Requires-Dist: PyKCS11>=1.5.12; extra == "all"
Requires-Dist: pytest>=6.2.5; extra == "all"
Requires-Dist: pytest-cov>=2.12.1; extra == "all"
Requires-Dist: black>=21.9b0; extra == "all"
Requires-Dist: flake8>=3.9.2; extra == "all"
Requires-Dist: mypy>=0.910; extra == "all"
Requires-Dist: sphinx>=4.2.0; extra == "all"
Requires-Dist: sphinx-rtd-theme>=1.0.0; extra == "all"
Dynamic: author
Dynamic: home-page
Dynamic: license-file
Dynamic: maintainer
Dynamic: platform
Dynamic: requires-python
